tcegoframework/__init__.py
tcegoframework/__main__.py
tcegoframework/cfgparsing.py
tcegoframework/cli.py
tcegoframework/config.py
tcegoframework/dremio.py
tcegoframework/io.py
tcegoframework/tcehdfs.py
tcegoframework/data/__init__.py
tcegoframework/data/filter.py
tcegoframework/data/misc.py
tcegoframework/data/inference/__init__.py
tcegoframework/data/inference/utils.py
tcegoframework/flows/__init__.py
tcegoframework/flows/evaluation.py
tcegoframework/flows/inference.py
tcegoframework/flows/training.py
tcegoframework/model/__init__.py
tcegoframework/model/bert.py
tcegoframework/model/metrics.py
tcegoframework/preprocessing/__init__.py
tcegoframework/preprocessing/anomalydetection.py
tcegoframework/preprocessing/classification.py
tcegoframework/preprocessing/encoders.py
tcegoframework/preprocessing/text.py
tcegoframework/preprocessing/transform.py
tcegoframework/resources/__init__.py
tcegoframework/resources/dremio-jdbc-driver.jar
tcegoframework-0.6.3.dist-info/LICENSE
tcegoframework-0.6.3.dist-info/METADATA
tcegoframework-0.6.3.dist-info/WHEEL
tcegoframework-0.6.3.dist-info/entry_points.txt
tcegoframework-0.6.3.dist-info/top_level.txt
tcegoframework-0.6.3.dist-info/RECORD
