Metadata-Version: 2.1
Name: tcegoframework
Version: 0.6.3
Summary: TCE-GO Artificial Intelligence Framework
Home-page: https://github.com/Kinteshi/TCE-GO-AI-Framework
Author: Kinteshi
Author-email: kinteshi@outlook.com
License: UNKNOWN
Project-URL: Bug Tracker, https://github.com/Kinteshi/TCE-GO-AI-Framework/issues
Platform: UNKNOWN
Classifier: Programming Language :: Python :: 3
Classifier: License :: OSI Approved :: GNU Affero General Public License v3 or later (AGPLv3+)
Classifier: Operating System :: OS Independent
Requires-Python: >=3.8
License-File: LICENSE
Requires-Dist: dill
Requires-Dist: numpy
Requires-Dist: pandas
Requires-Dist: seaborn
Requires-Dist: matplotlib
Requires-Dist: clean-text
Requires-Dist: unidecode
Requires-Dist: torch
Requires-Dist: tensorflow
Requires-Dist: transformers
Requires-Dist: scipy
Requires-Dist: sklearn
Requires-Dist: nltk
Requires-Dist: openpyxl
Requires-Dist: jaydebeapi
Requires-Dist: pexpect
Requires-Dist: hdfs3
